{
  "name": "Armor",
  "type": "vehicle_gear",
  "effects": [],
  "folder": null,
  "sort": 0,
  "flags": {
    "core": {}
  },
  "_id": "SfP8hCsEW7EwLDvo",
  "_stats": {
    "coreVersion": "13.351",
    "systemId": "beamsaber",
    "systemVersion": "0.6.0",
    "createdTime": null,
    "modifiedTime": 1773942293405,
    "lastModifiedBy": "YR7rqLkjCwcJpOjY",
    "compendiumSource": "Item.5RTIXU9d5Ach2TAg",
    "duplicateSource": null,
    "exportSource": null
  },
  "ownership": {
    "default": 0,
    "JVvMbwnked5Yb4AD": 3
  },
  "system": {
    "description": "<p>[Load 2] Spend to reduce Damage by one level. Armor is restored at the start of downtime at no cost. Armor can be taken multiple times-each costs 2 Load and can be spent once per mission.</p>",
    "logic": "",
    "activation": {
      "type": "",
      "cost": 0,
      "condition": ""
    },
    "duration": {
      "value": null,
      "units": ""
    },
    "target": {
      "value": null,
      "width": null,
      "units": "",
      "type": ""
    },
    "range": {
      "value": null,
      "long": null,
      "units": ""
    },
    "uses": {
      "value": 0,
      "max": 0,
      "per": null
    },
    "consume": {
      "type": "",
      "target": null,
      "amount": null
    },
    "owner": null,
    "is_container": false,
    "container_load": 0,
    "container_item_types": [],
    "class": "",
    "load": 2,
    "form": 0,
    "suppressed": false,
    "experimental": false,
    "hidden": false,
    "special_ammunition_type": "other",
    "armor": true
  },
  "img": "icons/svg/item-bag.svg",
  "_key": "!items!SfP8hCsEW7EwLDvo"
}
